[
    {
        "questionText": "Что необходимо доливать в систему охлаждения автогрейдера, заправленную антифризом, если объем жидкости уменшился за счет испарения, а не за счет течи?",
        "questionImage": "",
        "rightAnswer": 0,
        "answers": [
            "Только антифриз.",
            "Только воду.",
            "Не имеет значения."
        ]
    },
    {
        "questionText": "Какое давление воздуха в шинах автогрейдера ГС-14.02?",
        "questionImage": "",
        "rightAnswer": 0,
        "answers": [
            "0,15 - 0,20 МПа (1,5 - 2,0 кгс/см2).",
            "0,20 - 0,25 МПа (2,0 - 2,5 кгс/см2).",
            "0,25 - 0,40 МПа (2,5 - 3,0 кгс/см2)."
        ]
    },
    {
        "questionText": "Какое минимальное значение давления должно быть в пневмосистеме тягача самоходного скрепера перед троганием с места?",
        "questionImage": "",
        "rightAnswer": 0,
        "answers": [
            "0,35 МПа (3,5 кгс/см2).",
            "0,45 МПа (4,5 кгс/см2).",
            "0,55 МПа (5,5 кгс/см2)."
        ]
    },
    {
        "questionText": "Что должен сделать оператор для наблюдения за разгрузкой самосвала и работой бункера?",
        "questionImage": "",
        "rightAnswer": 0,
        "answers": [
            "Встать со своего сиденья.",
            "Пересесть на сиденье с левого борта.",
            "Пересесть на сиденье с правого борта.",
            "Сиденье может выдвигаться в сторону."
        ]
    },
    {
        "questionText": "Какой тип имеет рабочий орган катка \"Амкодор 68111 К\"?",
        "questionImage": "",
        "rightAnswer": 0,
        "answers": [
            "Два гладвких вибровальца.",
            "Кулачковый вибрационный валец.",
            "Один гладкий вибрационный валец."
        ]
    },
    {
        "questionText": "Снизилось давление наддува (дизель дымит и не развивает полной мощности). Какова вероятная причина?",
        "questionImage": "",
        "rightAnswer": 0,
        "answers": [
            "Нарушена герметичность крепления турбокомпрессора.",
            "Загрязнен масляный фильтр.",
            "Засорился воздухоочиститель.",
            "Вероятны 1-я и 3-я причины."
        ]
    },
    {
        "questionText": "Какой максимально допустимый поперечный уклон эксплуатации у катка ДС-30 без балласта?",
        "questionImage": "",
        "rightAnswer": 0,
        "answers": [
            "12°.",
            "17°.",
            "18°."
        ]
    },
    {
        "questionText": "При какой из указанных причин стартер при включении вращается с малой частотой?",
        "questionImage": "",
        "rightAnswer": 0,
        "answers": [
            "Обрыв в цепи стартера.",
            "Разряжена аккумуляторная батарея.",
            "Замыкание электропроводки."
        ]
    },
    {
        "questionText": "Запуская двигатель Д-260 при низких температурах, нужно ли придерживать клавишу ЛВЖ (легковоспламеняющаяся жидкость) до начала устойчивой работы?",
        "questionImage": "",
        "rightAnswer": 0,
        "answers": [
            "Нет.",
            "По желанию оператора асфальтоукладчика.",
            "Да."
        ]
    },
    {
        "questionText": "Через сколько моточасов необходимо производить замену фильтрующего элемента в фильтре гидромасла виброкатка 3414 Р?",
        "questionImage": "",
        "rightAnswer": 0,
        "answers": [
            "Через 125 мото/ч.",
            "Через 250 мото/ч.",
            "Через 500 мото/ч.",
            "Через 100 мото/ч."
        ]
    }
]